setup.py
aliyun_oss/__init__.py
aliyun_oss/models.py
aliyun_oss/tests.py
aliyun_oss/views.py
aliyun_oss/backends/__init__.py
aliyun_oss/backends/oss.py
aliyun_oss/oss/__init__.py
aliyun_oss/oss/oss_api.py
aliyun_oss/oss/oss_sample.py
aliyun_oss/oss/oss_util.py
aliyun_oss/oss/oss_xml_handler.py
aliyun_oss/oss/pkg_info.py
django_aliyun_oss.egg-info/PKG-INFO
django_aliyun_oss.egg-info/SOURCES.txt
django_aliyun_oss.egg-info/dependency_links.txt
django_aliyun_oss.egg-info/not-zip-safe
django_aliyun_oss.egg-info/pbr.json
django_aliyun_oss.egg-info/top_level.txt