Metadata-Version: 1.1
Name: django-aliyun-oss
Version: 0.3.1
Summary: django aliyun oss backend
Home-page: https://github.com/YuelianINC
Author: WANG Tai
Author-email: wangtai@bugua.com
License: Apache2
Platform: UNKNOWN
Classifier: Development Status :: 4 - Beta
Classifier: Environment :: Web Environment
Classifier: Framework :: Django
Classifier: Intended Audience :: Developers
Classifier: Natural Language :: English
Classifier: Operating System :: POSIX :: Linux
Classifier: Programming Language :: Python
Classifier: Topic :: System :: Installation/Setup
Requires: Django
Requires: alioss
